CUDAInline/Context.py
CUDAInline/DVBuffer.py
CUDAInline/DVCombine.py
CUDAInline/DVVector.py
CUDAInline/DeviceViewable.py
CUDAInline/Native.py
CUDAInline/PyCUDAInline.dll
CUDAInline/__init__.py
CUDAInline/cffi.py
CUDAInline/libPyCUDAInline.so
CUDAInline/utils.py
CUDAInline-0.0.6.dist-info/METADATA
CUDAInline-0.0.6.dist-info/WHEEL
CUDAInline-0.0.6.dist-info/top_level.txt
CUDAInline-0.0.6.dist-info/RECORD
