Metadata-Version: 2.1
Name: CUDAInline
Version: 0.0.6
Summary: A CUDA interface for Python
Home-page: https://github.com/fynv/CUDAInline
Author: Fei Yang
Author-email: hyangfeih@gmail.com
License: Anti 996
Keywords: GPU CUDA Python NVRTC
Platform: UNKNOWN
Requires-Dist: cffi
Requires-Dist: numpy
